xivuniversalis/__init__.py
xivuniversalis/client.py
xivuniversalis/decorators.py
xivuniversalis/errors.py
xivuniversalis/models.py
xivuniversalis-0.1.0a2.dist-info/METADATA
xivuniversalis-0.1.0a2.dist-info/WHEEL
xivuniversalis-0.1.0a2.dist-info/licenses/LICENSE
xivuniversalis-0.1.0a2.dist-info/RECORD
